aippt_mcp/__init__.py
aippt_mcp/server.py
aippt_mcp-0.0.4.dist-info/licenses/LICENSE
aippt_mcp-0.0.4.dist-info/METADATA
aippt_mcp-0.0.4.dist-info/WHEEL
aippt_mcp-0.0.4.dist-info/entry_points.txt
aippt_mcp-0.0.4.dist-info/top_level.txt
aippt_mcp-0.0.4.dist-info/RECORD
