Metadata-Version: 2.4
Name: aippt-mcp
Version: 0.0.4
Summary: AIPPT-MCP: 讯飞智能PPT生成服务MCPServer，支持MCP协议和uvx一键启动。
Author-email: gyli16 <gyli16@iflytek.com>
License: MIT
Classifier: Programming Language :: Python :: 3
Classifier: License :: OSI Approved :: MIT License
Classifier: Operating System :: OS Independent
Requires-Python: >=3.10
License-File: LICENSE
Requires-Dist: mcp[cli]>=1.3.0
Requires-Dist: requests
Requires-Dist: requests_toolbelt
Dynamic: license-file
